Metadata-Version: 2.1
Name: shobanaCalculator
Version: 0.0.2
Summary: A very basic calculator
Home-page: UNKNOWN
Author: shobana
Author-email: shobana.ramasamy@geekfactory.tech
License: MIT
Keywords: calculator
Platform: UNKNOWN
Classifier: Development Status :: 5 - Production/Stable
Classifier: Intended Audience :: Education
Classifier: License :: OSI Approved :: MIT License
Classifier: Programming Language :: Python :: 3
License-File: LICENCE.txt
